AUTHORS.rst
HISTORY.rst
MANIFEST.in
README.rst
requirements.txt
setup.py
ppytools/__init__.py
ppytools/cfgreader.py
ppytools/cfgreader2.py
ppytools/cfgreader3.py
ppytools/compresshelper.py
ppytools/csvhelper2.py
ppytools/csvhelper3.py
ppytools/emailclient.py
ppytools/hiveclient.py
ppytools/ip2location2.py
ppytools/ip2location3.py
ppytools/mysqlclient.py
ppytools2.egg-info/PKG-INFO
ppytools2.egg-info/SOURCES.txt
ppytools2.egg-info/dependency_links.txt
ppytools2.egg-info/requires.txt
ppytools2.egg-info/top_level.txt
ppytools/excepts/__init__.py
ppytools/excepts/emailexcept.py
ppytools/lang/__init__.py
ppytools/lang/strings.py
ppytools/lang/timerhelper.py